pyspacer-0.12.0.dist-info/licenses/license.txt
spacer/.coverage
spacer/__init__.py
spacer/config.py
spacer/data_classes.py
spacer/exceptions.py
spacer/mailman.py
spacer/messages.py
spacer/storage.py
spacer/task_utils.py
spacer/tasks.py
spacer/train_classifier.py
spacer/train_utils.py
spacer/.ruff_cache/.gitignore
spacer/.ruff_cache/CACHEDIR.TAG
spacer/.ruff_cache/0.7.3/16050823238852742169
spacer/extractors/__init__.py
spacer/extractors/base.py
spacer/extractors/efficientnet.py
spacer/extractors/efficientnet_utils.py
spacer/extractors/torch_extractors.py
spacer/extractors/utils.py
spacer/extractors/vgg16.py
pyspacer-0.12.0.dist-info/METADATA
pyspacer-0.12.0.dist-info/WHEEL
pyspacer-0.12.0.dist-info/top_level.txt
pyspacer-0.12.0.dist-info/RECORD
