Metadata-Version: 2.4
Name: pyspacer
Version: 0.12.0
Summary: Spatial image analysis with pytorch and caffe backends.
Author-email: Oscar Beijbom <oscar.beijbom@gmail.com>
License: MIT License
Project-URL: Homepage, https://github.com/coralnet/pyspacer
Classifier: Programming Language :: Python :: 3
Classifier: License :: OSI Approved :: MIT License
Classifier: Operating System :: OS Independent
Requires-Python: >=3.10
License-File: license.txt
Requires-Dist: Pillow>=10.4.0
Requires-Dist: numpy<2.2,>=1.22
Requires-Dist: scikit-learn==1.5.2
Requires-Dist: torch<2.7,>=2.6
Requires-Dist: torchvision<0.22,>=0.21
Requires-Dist: boto3>=1.26.115
Dynamic: license-file
